setup.py
digLshClustering/__init__.py
digLshClustering/copyFiles.py
digLshClustering/count_keys.py
digLshClustering/csvtojson.py
digLshClustering/runLSH.py
digLshClustering/sequenceToText.py
digLshClustering.egg-info/PKG-INFO
digLshClustering.egg-info/SOURCES.txt
digLshClustering.egg-info/dependency_links.txt
digLshClustering.egg-info/requires.txt
digLshClustering.egg-info/top_level.txt
digLshClustering/clusterer/__init__.py
digLshClustering/clusterer/clusterer.py
digLshClustering/clusterer/unionFind.py
digLshClustering/clusterer/old/__init__.py
digLshClustering/clusterer/old/cluster_dedup_mapper.py
digLshClustering/clusterer/old/cluster_dedup_reducer.py
digLshClustering/clusterer/old/cluster_jsonoutput_mapper.py
digLshClustering/clusterer/old/cluster_jsonoutput_reducer.py
digLshClustering/clusterer/old/cluster_mapper.py
digLshClustering/clusterer/old/cluster_mean_reducer.py
digLshClustering/clusterer/old/cluster_reducer.py
digLshClustering/clusterer/old/findSimilarity.py
digLshClustering/clusterer/old/genClusters.py
digLshClustering/clusterer/old/genClustersWithBase.py
digLshClustering/clusterer/old/mr_cluster_similarity_mapper.py
digLshClustering/clusterer/old/mr_cluster_similarity_reducer.py
digLshClustering/clusterer/old/mr_clusterid_size_mapper.py
digLshClustering/clusterer/old/mr_clusterid_size_reducer.py
digLshClustering/clusterer/old/mr_key_clusterid_mapper.py
digLshClustering/clusterer/old/mr_key_clusterid_reducer.py
digLshClustering/clusterer/old/mr_lsh_clusterid_mapper.py
digLshClustering/clusterer/old/mr_lsh_clusterid_reducer.py
digLshClustering/clusterer/old/unionFind.py
digLshClustering/hasher/__init__.py
digLshClustering/hasher/hasher.py
digLshClustering/hasher/lsh/__init__.py
digLshClustering/hasher/lsh/lsh.py
digLshClustering/hasher/lsh/unionfind.py
digLshClustering/hasher/old/__init__.py
digLshClustering/hasher/old/genLSH.py
digLshClustering/hasher/old/genMinhash.py
digLshClustering/hasher/old/mr_int_lsh_mapper.py
digLshClustering/hasher/old/mr_lsh_reducer.py
digLshClustering/hasher/old/mr_str_lsh_mapper.py
digLshClustering/utils/__init__.py
digLshClustering/utils/address.py
digLshClustering/utils/util.py